[{"line":1,"elements":[{"start_timestamp":"2023-12-27T09:25:30.967Z","before":[{"result":{"duration":5569662900,"status":"passed"},"match":{"location":"StepDefinitions.RegistrationStepDefinition.setupbrowser()"}}],"line":3,"name":"Successful user registration","description":"","id":"user-registrations-and-login-validations;successful-user-registration","after":[{"result":{"duration":777525400,"status":"passed"},"match":{"location":"StepDefinitions.RegistrationStepDefinition.CloseBrowser()"}}],"type":"scenario","keyword":"Scenario","steps":[{"result":{"duration":11958735200,"status":"passed"},"line":4,"name":"user is on Application registration page","match":{"location":"StepDefinitions.RegistrationStepDefinition.user_is_on_application_registration_page()"},"keyword":"Given "},{"result":{"duration":1563021400,"status":"passed"},"line":5,"name":"user provides username Password and confirm password","match":{"location":"StepDefinitions.RegistrationStepDefinition.user_provides_username_password_and_confirmpassword()"},"keyword":"And "},{"result":{"duration":3078694600,"status":"passed"},"line":6,"name":"user clicks on submit button","match":{"location":"StepDefinitions.RegistrationStepDefinition.user_clicks_on_submit_button()"},"keyword":"When "},{"result":{"duration":317213400,"status":"passed"},"line":7,"name":"verify if user registered successfully","match":{"location":"StepDefinitions.RegistrationStepDefinition.user_registered_succesfully()"},"keyword":"Then "}],"tags":[{"name":"@registartion"}]},{"start_timestamp":"2023-12-27T09:25:54.260Z","before":[{"result":{"duration":5114694800,"status":"passed"},"match":{"location":"StepDefinitions.RegistrationStepDefinition.setupbrowser()"}}],"line":10,"name":"Validate User is able to Login with Valid Credentials","description":"","id":"user-registrations-and-login-validations;validate-user-is-able-to-login-with-valid-credentials","after":[{"result":{"duration":621955500,"status":"passed"},"match":{"location":"StepDefinitions.RegistrationStepDefinition.CloseBrowser()"}}],"type":"scenario","keyword":"Scenario","steps":[{"result":{"duration":8869232300,"status":"passed"},"line":11,"name":"user is on Application Landing Page","match":{"location":"StepDefinitions.LoginStepDefenition.user_is_on_application_landing_page()"},"keyword":"Given "},{"result":{"duration":256898700,"status":"passed"},"line":12,"name":"user enters valid username and Password","match":{"location":"StepDefinitions.LoginStepDefenition.user_enters_username_password()"},"keyword":"And "},{"result":{"duration":8585241000,"status":"passed"},"line":13,"name":"user clicks on login button","match":{"location":"StepDefinitions.LoginStepDefenition.user_clicks_on_login_button()"},"keyword":"When "},{"result":{"duration":2232385900,"status":"passed"},"line":14,"name":"verify user logged in successfully","match":{"location":"StepDefinitions.LoginStepDefenition.verify_user_logged_in_succesfully()"},"keyword":"Then "}],"tags":[{"name":"@login"}]},{"start_timestamp":"2023-12-27T09:26:19.952Z","before":[{"result":{"duration":4745864300,"status":"passed"},"match":{"location":"StepDefinitions.RegistrationStepDefinition.setupbrowser()"}}],"line":17,"name":"Validate User is unable to Login with invalid credentials","description":"","id":"user-registrations-and-login-validations;validate-user-is-unable-to-login-with-invalid-credentials","after":[{"result":{"duration":595462900,"status":"passed"},"match":{"location":"StepDefinitions.RegistrationStepDefinition.CloseBrowser()"}}],"type":"scenario","keyword":"Scenario","steps":[{"result":{"duration":6590116100,"status":"passed"},"line":18,"name":"user is on Application Landing Page","match":{"location":"StepDefinitions.LoginStepDefenition.user_is_on_application_landing_page()"},"keyword":"Given "},{"result":{"duration":432536900,"status":"passed"},"line":19,"name":"user enters Invalid username and Password","match":{"location":"StepDefinitions.LoginStepDefenition.user_enters_Invalid_username_password()"},"keyword":"And "},{"result":{"duration":6736757800,"status":"passed"},"line":20,"name":"user clicks on login button","match":{"location":"StepDefinitions.LoginStepDefenition.user_clicks_on_login_button()"},"keyword":"When "},{"result":{"duration":218478700,"status":"passed"},"line":21,"name":"Verify user is not loggedin and invalid credentials message displayed","match":{"location":"StepDefinitions.LoginStepDefenition.verify_user_is_not_loggedin_and_invalid_credentials_message_displayed()"},"keyword":"And "}],"tags":[{"name":"@InvalidLogin"}]}],"name":"User Registrations and Login validations","description":"","id":"user-registrations-and-login-validations","keyword":"Feature","uri":"file:src/test/java/Features/RegistartionLogin.feature","tags":[]},{"line":2,"elements":[{"start_timestamp":"2023-12-27T09:26:39.282Z","before":[{"result":{"duration":4938400900,"status":"passed"},"match":{"location":"StepDefinitions.RegistrationStepDefinition.setupbrowser()"}}],"line":5,"name":"Validate User is able book flight ticket","description":"","id":"flight-booking;validate-user-is-able-book-flight-ticket","after":[{"result":{"duration":681134100,"status":"passed"},"match":{"location":"StepDefinitions.RegistrationStepDefinition.CloseBrowser()"}}],"type":"scenario","keyword":"Scenario","steps":[{"result":{"duration":8569238700,"status":"passed"},"line":6,"name":"user is on Application Landing Page","match":{"location":"StepDefinitions.LoginStepDefenition.user_is_on_application_landing_page()"},"keyword":"Given "},{"result":{"duration":11426034800,"status":"passed"},"line":7,"name":"user navigates to flight finderpage","match":{"location":"StepDefinitions.Flightbookingstepdef.user_navigates_to_flight_finderpage()"},"keyword":"And "},{"result":{"duration":161507000,"status":"passed"},"line":8,"name":"user chooses  passengers count","match":{"location":"StepDefinitions.Flightbookingstepdef.user_chooses_passengers()"},"keyword":"When "},{"result":{"duration":210152800,"status":"passed"},"line":9,"name":"user selects From port","match":{"location":"StepDefinitions.Flightbookingstepdef.user_selects_from_port()"},"keyword":"And "},{"result":{"duration":292066300,"status":"passed"},"line":10,"name":"user Selects on Month and Day","match":{"location":"StepDefinitions.Flightbookingstepdef.user_selects_on_month_and_day()"},"keyword":"And "},{"result":{"duration":123186200,"status":"passed"},"line":11,"name":"user selects To port","match":{"location":"StepDefinitions.Flightbookingstepdef.user_selects_to_port()"},"keyword":"And "},{"result":{"duration":255072200,"status":"passed"},"line":12,"name":"user Selects Returing Month and Day","match":{"location":"StepDefinitions.Flightbookingstepdef.user_selects_returing_month_and_day()"},"keyword":"And "},{"result":{"duration":402072300,"status":"passed"},"line":13,"name":"user selects Biussness class and Airline","match":{"location":"StepDefinitions.Flightbookingstepdef.user_selects_biussness_class_and_airline()"},"keyword":"And "},{"result":{"duration":1564045500,"status":"passed"},"line":14,"name":"user clicks on Continue Button","match":{"location":"StepDefinitions.Flightbookingstepdef.user_clicks_on_continue_button()"},"keyword":"And "},{"result":{"duration":251083300,"status":"passed"},"line":15,"name":"Verify if the Flight is booked succesfully","match":{"location":"StepDefinitions.Flightbookingstepdef.verify_if_the_flight_is_booked_succesfully()"},"keyword":"Then "}],"tags":[{"name":"@three"}]}],"name":"Flight Booking","description":"","id":"flight-booking","keyword":"Feature","uri":"file:src/test/java/Features/flightbooking.feature","tags":[]}]